kingorm/__init__.py
kingorm/__main__.py
kingorm/migration.py
kingorm/model.py
kingorm/strings.py
kingorm-1.0.0.dist-info/LICENSE
kingorm-1.0.0.dist-info/METADATA
kingorm-1.0.0.dist-info/WHEEL
kingorm-1.0.0.dist-info/top_level.txt
kingorm-1.0.0.dist-info/RECORD
