Metadata-Version: 2.1
Name: kingorm
Version: 1.0.0
Summary: King is an ORM for Python and SQLite. It is designed to be a lightweight solution for simple programs, where objects have to be stored. A programmer just needs to define fields in the model classes and that's it!
Home-page: https://github.com/king-orm/orm/
Author: Anatoly Frolov
Author-email: contact@anafro.ru
License: MIT
Classifier: Development Status :: 1 - Planning
Classifier: Intended Audience :: Science/Research
Classifier: Intended Audience :: Developers
Classifier: License :: OSI Approved :: MIT License
Classifier: Programming Language :: Python :: 3.11
Classifier: Programming Language :: SQL
Classifier: Operating System :: OS Independent
License-File: LICENSE
